<?xml version="1.0" encoding="utf-8"?>
<search>
  
  
  
  <entry>
    <title>Hexo初体验</title>
    <link href="/2020/03/03/hello-world/"/>
    <url>/2020/03/03/hello-world/</url>
    
    <content type="html"><![CDATA[<link rel="stylesheet" class="aplayer-secondary-style-marker" href="\assets\css\APlayer.min.css"><script src="\assets\js\APlayer.min.js" class="aplayer-secondary-script-marker"></script><script class="meting-secondary-script-marker" src="\assets\js\Meting.min.js"></script><p>用Hexo搭建一个blog~<br><a id="more"></a></p><h2 id="Hexo相关命令"><a href="#Hexo相关命令" class="headerlink" title="Hexo相关命令"></a>Hexo相关命令</h2><h3 id="写一篇文章"><a href="#写一篇文章" class="headerlink" title="写一篇文章"></a>写一篇文章</h3><pre><code class="lang-bash">$ hexo new &quot;Hexo初体验&quot;</code></pre><h3 id="本地启动Hexo服务"><a href="#本地启动Hexo服务" class="headerlink" title="本地启动Hexo服务"></a>本地启动Hexo服务</h3><pre><code class="lang-bash">$ hexo server 或 hexo s</code></pre><h3 id="生成静态文件"><a href="#生成静态文件" class="headerlink" title="生成静态文件"></a>生成静态文件</h3><pre><code class="lang-bash">$ hexo generate 或 hexo g</code></pre><h3 id="部署"><a href="#部署" class="headerlink" title="部署"></a>部署</h3><pre><code class="lang-bash">$ hexo deploy 或 hexo d</code></pre>]]></content>
    
    
    <categories>
      
      <category>Hexo</category>
      
    </categories>
    
    
    <tags>
      
      <tag>Hexo</tag>
      
    </tags>
    
  </entry>
  
  
  
  
</search>
